fastapi_views/__init__.py
fastapi_views/cli.py
fastapi_views/config.py
fastapi_views/exceptions.py
fastapi_views/filters/__init__.py
fastapi_views/filters/dependencies.py
fastapi_views/filters/models.py
fastapi_views/filters/operations.py
fastapi_views/filters/resolvers/__init__.py
fastapi_views/filters/resolvers/abc.py
fastapi_views/filters/resolvers/objects.py
fastapi_views/filters/resolvers/sqlalchemy.py
fastapi_views/filters/types.py
fastapi_views/handlers.py
fastapi_views/models.py
fastapi_views/opentelemetry.py
fastapi_views/pagination.py
fastapi_views/prometheus.py
fastapi_views/py.typed
fastapi_views/router.py
fastapi_views/types.py
fastapi_views/views/__init__.py
fastapi_views/views/api.py
fastapi_views/views/functools.py
fastapi_views/views/generics.py
fastapi_views/views/mixins.py
fastapi_views/views/viewsets.py
fastapi_views-1.4.0.dist-info/WHEEL
fastapi_views-1.4.0.dist-info/entry_points.txt
fastapi_views-1.4.0.dist-info/METADATA
fastapi_views-1.4.0.dist-info/RECORD
