Metadata-Version: 2.4
Name: fastapi-views
Version: 1.4.0
Summary: FastAPI Class Views and utilities
Keywords: fastapi,views,asyncio
Author: RaRhAeu
Author-email: RaRhAeu <rarha_eu@protonmail.com>
License-Expression: Apache-2.0
Classifier: Operating System :: OS Independent
Classifier: Programming Language :: Python :: 3
Classifier: Programming Language :: Python
Classifier: Topic :: Internet
Classifier: Topic :: Software Development :: Libraries :: Application Frameworks
Classifier: Topic :: Software Development :: Libraries :: Python Modules
Classifier: Topic :: Software Development :: Libraries
Classifier: Topic :: Software Development
Classifier: Typing :: Typed
Classifier: Development Status :: 4 - Beta
Classifier: Environment :: Web Environment
Classifier: Framework :: AsyncIO
Classifier: Framework :: FastAPI
Classifier: Framework :: Pydantic
Classifier: Framework :: Pydantic :: 2
Classifier: Intended Audience :: Developers
Classifier: Programming Language :: Python :: Implementation :: CPython
Classifier: Programming Language :: Python :: Implementation :: PyPy
Classifier: Programming Language :: Python :: 3 :: Only
Classifier: Programming Language :: Python :: 3.8
Classifier: Programming Language :: Python :: 3.9
Classifier: Programming Language :: Python :: 3.10
Classifier: Programming Language :: Python :: 3.11
Classifier: Programming Language :: Python :: 3.12
Classifier: Programming Language :: Python :: 3.13
Classifier: Programming Language :: Python :: 3.14
Classifier: Topic :: Internet :: WWW/HTTP :: HTTP Servers
Classifier: Topic :: Internet :: WWW/HTTP
Requires-Dist: fastapi
Requires-Dist: pydantic>2.0,<3
Requires-Dist: uvloop ; extra == 'all'
Requires-Dist: starlette-exporter ; extra == 'all'
Requires-Dist: uvicorn ; extra == 'all'
Requires-Dist: opentelemetry-instrumentation-fastapi ; extra == 'all'
Requires-Dist: typer ; extra == 'all'
Requires-Dist: typer ; extra == 'cli'
Requires-Dist: opentelemetry-instrumentation-fastapi ; extra == 'opentelemetry'
Requires-Dist: starlette-exporter ; extra == 'prometheus'
Requires-Dist: uvicorn ; extra == 'uvicorn'
Requires-Dist: uvloop ; extra == 'uvloop'
Requires-Python: >=3.9
Project-URL: Documentation, https://github.com/asynq-io/fastapi-views#readme
Project-URL: Issues, https://github.com/asynq-io/fastapi-views/issues
Project-URL: Source, https://github.com/asynq-io/fastapi-views
Provides-Extra: all
Provides-Extra: cli
Provides-Extra: opentelemetry
Provides-Extra: prometheus
Provides-Extra: uvicorn
Provides-Extra: uvloop
